tests/__init__.py
tests/conftest.py
tests/test_basic.py
tests/test_conversion.py
zim2epub/__init__.py
zim2epub/cli.py
zim2epub/converter/__init__.py
zim2epub/converter/article_extractor.py
zim2epub/converter/full_crawl_extractor.py
zim2epub/converter/image_processor.py
zim2epub/converter/metadata.py
zim2epub/converter/toc_generator.py
zim2epub/converter/zim_to_epub.py
zim2epub/utils/__init__.py
zim2epub/utils/html_utils.py
zim2epub/utils/logging_utils.py
zim2epub/utils/path_utils.py
zim2epub-0.1.4.dist-info/LICENSE
zim2epub-0.1.4.dist-info/METADATA
zim2epub-0.1.4.dist-info/WHEEL
zim2epub-0.1.4.dist-info/entry_points.txt
zim2epub-0.1.4.dist-info/top_level.txt
zim2epub-0.1.4.dist-info/RECORD
