Metadata-Version: 2.1
Name: zim2epub
Version: 0.1.4
Summary: Convert ZIM files to EPUB format
Home-page: https://github.com/izzoa/zim2epub
Author: Anthony Izzo
Author-email: izzo.anthony@gmail.com
Classifier: Programming Language :: Python :: 3
Classifier: License :: OSI Approved :: MIT License
Classifier: Operating System :: OS Independent
Classifier: Development Status :: 3 - Alpha
Classifier: Intended Audience :: End Users/Desktop
Classifier: Topic :: Text Processing :: Markup :: XML
Requires-Python: >=3.6
License-File: LICENSE
Requires-Dist: libzim >=3.0.0
Requires-Dist: ebooklib >=0.17.1
Requires-Dist: beautifulsoup4 >=4.9.0
Requires-Dist: argparse >=1.4.0
Requires-Dist: tqdm >=4.45.0
Requires-Dist: lxml >=4.5.0
